Workbook
Name Beg_Bal: #REF!
Name Chinthi: '[1]P&L'!#REF!
Name Cum_Int: #REF!
Name Data: #REF!
Name End_Bal: #REF!
Name Extra_Pay: #REF!
Name Full_Print: #REF!
Name Header_Row: ROW(#REF!)
Name Int: #REF!
Name Interest_Rate: #REF!
Name Last_Row: IF(Values_Entered,Header_Row+Number_of_Payments,Header_Row)
Name Loan_Amount: #REF!
Name Loan_Start: #REF!
Name Loan_Years: #REF!
Name Num_Pmt_Per_Year: #REF!
Name Number_of_Payments: MATCH(0.01,End_Bal,-1)+1
Name Pay_Date: #REF!
Name Pay_Num: #REF!
Name Payment_Date: DATE(YEAR(Loan_Start),MONTH(Loan_Start)+Payment_Number,DAY(Loan_Start))
Name Princ: #REF!
Name Print_Area_Reset: OFFSET(Full_Print,0,0,Last_Row)
Name ranji: '[1]P&L'!#REF!
Name Sched_Pay: #REF!
Name Scheduled_Extra_Payments: #REF!
Name Scheduled_Interest_Rate: #REF!
Name Scheduled_Monthly_Payment: #REF!
Name Total_Interest: #REF!
Name Total_Pay: #REF!
Name Values_Entered: IF(Loan_Amount*Interest_Rate*Loan_Years*Loan_Start>0,1,0)
Name vDateTime: #REF!
Name vDiastolic: #REF!
Name vHeartRate: #REF!
Name vSystolic: #REF!

Sheet PPE
A1: Fixed Asset Register
A3: Asset | B3: Month of purchased | C3: Rate | D3: Amount | E3: Month starting Depreciation | F3: Date | G3: Depreciation Amount
A4: Furniture & Fittings | B4: 45385 | C4: 5 | D4: 153700 | E4: 45728 | F4: =E4-B4 -> 343 | G4: =(D4/C4)*(F4/365) -> 28887.178
A5: Total | D5: =SUM(D4:D4) -> 153700 | G5: =SUM(G4:G4) -> 28887.178

Sheet Working
A1: Income
A2: Interest Income | B2: 2328236
A4: Administrative Expenses
A5: Advertisment & Sales Promotion | B5: 99975
A6: Bad Debts | B6: 163480
A8: Assets | C8: Bill Nu.
A11: EPF ETF
A12: EPF & ETF | B12: EPF20% | C12: EPF12% | D12: ETF3%
A13: 45597 | B13: 4200 | C13: =B13*12/20 -> 2520 | D13: =C13*3/12 -> 630
A14: Total | B14: =SUM(B13:B13) -> 4200 | C14: =SUM(C13:C13) -> 2520 | D14: =SUM(D13:D13) -> 630

Sheet TB
A1: N K R S Lanka Capital Pvt Ltd
A2: Trial Balance
A3: As at 31st March 2025
A4: Accounts | B4: Dr | C4: Cr
A5: Bank accounts
A6: Cash | B6: 12560
A7: Assets
A8: Furniture & Fittings | B8: =+PPE!D4 -> 153700
A9: Accumalated Deprecion | C9: =+PPE!G5 -> 28887.178
A10: Liabilities
A11: Accountany Fee | C11: =+B24 -> 15000
A12: Audit Fee | C12: =+B26 -> 25000
A13: Equity
A14: Share capital | C14: =1000*6 -> 6000
A15: Director C/A - Invetment | C15: 1000000
A16: Income
A17: Receivables | B17: 112919.5
A18: Interest Income | C18: =+Working!B2 -> 2328236
A19: Expenses
A20: EPF | B20: 12600
A21: ETF | B21: 3150
A22: Dirtectors remuniration | B22: 1220000
A23: Income Tax | B23: 1000
A24: Accountany Fee | B24: 15000
A25: Bad Debts | B25: =+Working!B6 -> 163480
A26: Audit Fee | B26: 25000
A27: Total | B27: =SUM(B5:B26) -> 1719409.5 | C27: =SUM(C5:C26) -> 3403123.2
B28: =B27-C27 -> -1683713.7

Sheet P11
A1: N K R S LANKA CAPITAL (PRIVATE) LIMITED | J1: Page 11
A2: NOTES TO THE FINANCIAL STATEMENTS
A3: AS AT 31ST MARCH | J3: 2025
J4: =[2]Income!D6 -> Rs
A6: 9 | B6: Cash & Cash Equivalent
B7: Cash In Hand | J7: =+TB!B6 -> 12560
J8: =SUM(J7:J7) -> 12560
A10: 10 | B10: Stated Capital
J11: Nos.
B12: Number of Shares - Ordinary Shares | J12: 6
J13: =SUM(J12) -> 6
J15: Rs.
B16: Value - Ordinary Shares | J16: =+TB!C14 -> 6000
J17: =SUM(J16) -> 6000
A19: 11 | B19: Trade Creditors & Other Payable
B20: EPF | J20: =TB!B20 -> 12600
B21: ETF | J21: =TB!B21 -> 3150
B22: Accountancy Fee | J22: =+TB!C11 -> 15000
B23: Audit Fee | J23: =+TB!C12 -> 25000
J24: =SUM(J20:J23) -> 55750

Sheet CE
A1: N K R S LANKA CAPITAL (PRIVATE) LIMITED | I1: Page 4
A2: STATEMENT OF CHANGES IN EQUITY
A3: FOR THE PERIOD ENDED 31ST MARCH 2025
E4: Stated Capital | G4: Retained Earnings | I4: Total
E5: Rs. | G5: Rs. | I5: Rs.
A7: Balance as at 01st April 2024 | E7: 0 | G7: 0 | I7: 0
A9: Shares Issued | E9: =+TB!C14 -> 6000 | G9: 0 | I9: =+E9 -> 6000
A11: Profit/(Loss) for the Period | E11: 0 | G11: =+PL!D16 -> 2123756 | I11: =G11 -> 2123756
A13: Balance as at 31st March 2025 | E13: =SUM(E7:E11) -> 6000 | G13: =SUM(G7:G11) -> 2123756 | I13: =SUM(I7:I11) -> 2129756
A21: Figures in brackets indicate deductions.
A23: The Notes on pages 06 to 11 form an integral part of these Financial Statements.

Sheet CF
A1: N K R S LANKA CAPITAL (PRIVATE) LIMITED | G1: Page 5
A2: STATEMENT OF CASH FLOWS
A3: =+PL!A3 -> FOR THE YEAR PERIOD 31ST MARCH | G3: 2025
G4: Rs.
A6: Cash flow from Operating Activities
A7: Net Profit before Taxation | G7: =+PL!D12 -> 2124756
A8: Adjustments For:
B9: Depreciation | G9: ='P09'!#REF! -> #REF!
A10: Operating Profit Before Working Capital Changes | G10: =SUM(G7:G9) -> #REF!
B12: (Increase)/Decrease in Receivables | G12: =-BS!E12 -> -112919.5
B13: Increase/(Decrease) in Trade Creditors & Other Payable | G13: =BS!E26 -> 55750
B14: Increase/(Decrease) in Director's Current Account | G14: =BS!E27 -> 1000000
A15: Cash Generated from Operations | G15: =SUM(G10:G14) -> #REF!
B17: Income Tax Paid | G17: =TB!B23 -> 1000
G18: =SUM(G17:G17) -> 1000
A19: Net Cash Flows from Operating Activities | G19: =SUM(G18+G15) -> #REF!
A21: Cash Flow from Investing Activities
B22: Property, Plant and Equipment | G22: =-'P10'!G7 -> -153700
A23: Net Cash Flow from/(Used in) Investing Activities | G23: =SUM(G22) -> -153700
A25: Cash flow from Financing Activities
B26: Shares Issued | G26: =+BS!E19 -> 6000
A27: Net Cash Used in Financing Activities | G27: =SUM(G26) -> 6000
A28: Net increase/ (Decrease) in Cash & Cash Equivalents | G28: =+G19+G23+G27 -> #REF!
B29: Cash & Cash Equivalents at the Beginning of the Period | G29: 0
B30: Cash & Cash Equivalents at the End of the Period | G30: =SUM(G28:G29) -> #REF!
A32: At the Beginning
B33: Cash in Hand | G33: 0
G34: =SUM(F33:F33) -> 0
A36: At the End
B37: Cash in Hand | G37: ='P11'!J7 -> 12560
G38: =SUM(G37:G37) -> 12560 | H38: =G30-G38 -> #REF!
A41: Figures in brackets indicate deductions.
A43: The Notes on pages 06 to 11 form an integral part of these Financial Statements.

Sheet PL
A1: N K R S LANKA CAPITAL (PRIVATE) LIMITED | D1: Page 2
A2: STATEMENT OF COMPREHENSIVE INCOME
A3: FOR THE YEAR PERIOD 31ST MARCH | D3: 2025
B4: Note | D4: Rs
A6: Revenue | B6: 4 | D6: =+'P09'!D8 -> 2328236
A8: Administration Expenses | B8: 5 | D8: =-'P09'!D13 -> -40000
A10: Finance Cost | B10: 6 | D10: =-'P09'!D17 -> -163480
A12: Profit/ (Loss) Before Taxation | D12: =SUM(D6:D10) -> 2124756
A14: Income Tax Expense | B14: 7 | D14: =-'P09'!D21 -> -1000
A16: Profit/ (Loss) for the Period | D16: =SUM(D12:D14) -> 2123756
A22: Figures in brackets indicate deductions.
A24: The Notes on pages 06 to 11 form an integral part of these Financial Statements.

Sheet BS
A1: N K R S LANKA CAPITAL (PRIVATE) LIMITED | E1: Page 3
A2: STATEMENT OF FINANCIAL POSITION
A3: AS AT 31ST MARCH 2025 | E3: 2025
C4: Note | E4: Rs.
A6: ASSETS
A7: Non Current Assets
A8: Property, Plant and Equipment | C8: 8 | E8: =+'P10'!J16 -> 124812.82
E9: =SUM(E8) -> 124812.82
A11: Current Assets
A12: Receivables | E12: =TB!B17 -> 112919.5
A13: Cash & Cash Equivalent | C13: 9 | E13: =+'P11'!J8 -> 12560
A14: Total Current Assets | E14: =SUM(E12:E13) -> 125479.5
A15: Total Assets | E15: =SUM(E14+E9) -> 250292.32
A17: EQUITY & LIABILITIES
A18: Capital and Reserve
A19: Stated Capital | C19: 10 | E19: =+'P11'!J17 -> 6000
A20: Retained Earnings | E20: =+CE!G13 -> 2123756
E21: =SUM(E19:E20) -> 2129756
A23: Non Current Liabilities | E23: 0
A25: Current Liabilities
A26: Trade Creditors & Other Payable | C26: 11 | E26: =+'P11'!J24 -> 55750
A27: Director's Current Account | E27: =TB!C15 -> 1000000
A28: Total Current Liabilities | E28: =SUM(E26:E27) -> 1055750
A29: Total Liabilities | E29: =E28+E23 -> 1055750
A30: Total Equity and Liabilities | E30: =+E21+E29 -> 3185506 | G30: =E15-E30 -> -2935213.7
A32: =+PL!A22 -> Figures in brackets indicate deductions. | G32: =G15-G30 -> 2935213.7
A34: =+PL!A24 -> The Notes on pages 06 to 11 form an integral part of these Financial Statements.
A36: These financial statements are in compliance with the requirements of Companies Act No. 07 of 2007.
A39: ……………………
A40: Accountant
A42: The Board of Directors is responsible for the preparation and presentation of these Financial Statements.
A43: Approved and Signed for and on behalf of the Board.
A47: …………………………… | D47: ……………………………
A48: (Director) | D48: (Director)
A50: 14th May 2026
A51: Kuruwita

Sheet P09
A1: N K R S LANKA CAPITAL (PRIVATE) LIMITED | D1: Page 9
A2: NOTES TO THE FINANCIAL STATEMENTS
A3: FOR THE PERIOD ENDED 31ST MARCH | D3: 2025
D4: Rs. | F4: 31/03/2023
F5: Rs.
A6: 4 | B6: Revenue
B7: Commission Income | D7: =+TB!C18 -> 2328236
D8: =D7 -> 2328236
A10: 5 | B10: Administration Expenses
B11: Accountancy Fee | D11: =+TB!B24 -> 15000
B12: Audit Fee | D12: =+TB!B26 -> 25000
D13: =SUM(D11:D12) -> 40000
A15: 6 | B15: Finance Cost
B16: Bad Debts | D16: =+TB!B25 -> 163480
D17: =SUM(D16) -> 163480
A19: 7 | B19: Income Tax Expense
B20: Current Tax Expense | D20: =TB!B23 -> 1000
D21: =+D20 -> 1000

Sheet P10
A1: N K R S LANKA CAPITAL (PRIVATE) LIMITED | J1: Page 10
A2: NOTES TO THE FINANCIAL STATEMENTS
A4: 8 | B4: Property, Plant and Equipment
B5: Cost | E5: Balance at 01.04.2024 | G5: Additions | H5: Disposal | J5: Balance at 31.03.2025
B6: =+TB!A8 -> Furniture & Fittings | E6: 0 | G6: =TB!B8 -> 153700 | J6: =SUM(E6:G6) -> 153700
E7: =SUM(E6:E6) -> 0 | G7: =SUM(G6:G6) -> 153700 | J7: =SUM(J6:J6) -> 153700
B10: Accumulated Depreciation | E10: Balance at 01.04.2024 | G10: Charge for the year | H10: Disposal | J10: Balance at 31.03.2025
B11: =B6 -> Furniture & Fittings | E11: 0 | G11: =PPE!G4 -> 28887.178 | J11: =SUM(E11:G11) -> 28887.178
E12: =SUM(E11:E11) -> 0 | G12: =SUM(G11:G11) -> 28887.178 | J12: =SUM(J11:J11) -> 28887.178
B14: Written Down Value | J14: Balance as at 31.03.2025
B15: =B11 -> Furniture & Fittings | J15: =J6-J11 -> 124812.82
J16: =SUM(J15:J15) -> 124812.82

Sheet Income Tax
A1: N K R S LANKA CAPITAL (PRIVATE) LIMITED | H1: Page 12
A2: COMPUTATION OF INCOME TAX
A3: YEAR OF ASSESSMENT 2024/2025
A4: TIN NO. 111350027
H5: Rs.
A6: Profit/(Loss) Before Tax as per Financial Statements | H6: =+PL!D12 -> 2124756
A8: Less: Exempt Amounts,Final Withholding Payments & Other Sources | H8: 0
H9: =SUM(H6:H8) -> 2124756
A10: Add: Deduction not Allowed
A11: Depreciation | F11: ='P10'!G12 -> 28887.178 | H11: =+F11 -> 28887.178
H12: =SUM(H9:H11) -> 2153643.2
A13: Less: Deduction Allowed
A14: Capital Allowances | F14: Annexure 1 | H14: =-E42 -> #REF!
A15: Assessable Income From Business/(Business Loss) | H15: =SUM(H12:H14) -> #REF!
A17: Taxable Income | H17: Loss
A19: Income Tax on Taxable Income | E19: @ 30% on | F19: =+H17 -> Loss | H19: =F19*0.3 -> #VALUE!
A21: Less : Tax Credits
A22: Self Assessment Income Tax Payments | E22: 24252 | F22: 0 | H22: =-SUM(F22:F22) -> 0
A24: Balance Tax Payable | H24: =SUM(H19:H22) -> #VALUE!
A27: Annexure to the Income Tax Computation
A29: Annexure 1 - Capital Allowances On Depreciable Assets
A31: Asset Description | B31: Cost | C31: Years | D31: Balance as at 01/04/2024 | E31: During the year Claim | F31: Balance as at 31/03/2025 | H31: WDV
A33: 2024/2025
A35: =+'P10'!B6 -> Furniture & Fittings | B35: =+'P10'!G6 -> 153700 | C35: 5 | D35: 0 | E35: =B35/C35 -> 30740 | F35: =D35+E35 -> 30740 | H35: =B35-F35 -> 122960
A36: =+'P10'!#REF! -> #REF! | B36: =+'P10'!#REF! -> #REF! | C36: 5 | D36: 0 | E36: =B36/C36 -> #REF! | F36: =D36+E36 -> #REF! | H36: =B36-F36 -> #REF!
A37: =+'P10'!#REF! -> #REF! | B37: =+'P10'!#REF! -> #REF! | C37: 5 | D37: 0 | E37: =B37/C37 -> #REF! | F37: =D37+E37 -> #REF! | H37: =B37-F37 -> #REF!
A38: =+'P10'!#REF! -> #REF! | B38: =+'P10'!#REF! -> #REF! | C38: 5 | D38: 0 | E38: =B38/C38 -> #REF! | F38: =D38+E38 -> #REF! | H38: =B38-F38 -> #REF!
A39: =+'P10'!#REF! -> #REF! | B39: =+'P10'!#REF! -> #REF! | C39: 5 | D39: 0 | E39: =B39/C39 -> #REF! | F39: =D39+E39 -> #REF! | H39: =B39-F39 -> #REF!
A40: =+'P10'!#REF! -> #REF! | B40: =+'P10'!#REF! -> #REF! | C40: 5 | D40: 0 | E40: =B40/C40 -> #REF! | F40: =D40+E40 -> #REF! | H40: =B40-F40 -> #REF!
A42: Total | B42: =SUM(B35:B40) -> #REF! | D42: =SUM(D35:D40) -> 0 | E42: =SUM(E35:E40) -> #REF! | F42: =SUM(F35:F40) -> #REF! | H42: =SUM(H35:H40) -> #REF!
A45: Annexure 2 - Business Losses
A46: Brought Forward from 2023/2024 | H46: 0
A47: Business Losses for the year | H47: =-H15 -> #REF!
H48: =SUM(H46:H47) -> #REF!
A50: Loss Deducted during the year
A51: Deducted against Investment Income | H51: 0
A52: Deducted against Business Income | H52: 0
A53: Carried Forward to 2025/2026 | H53: =SUM(H48:H52) -> #REF!
